{
  "place_id": 40415817,
  "licence": "Data © OpenStreetMap contributors, ODbL 1.0. http://osm.org/copyright",
  "osm_type": "way",
  "osm_id": 82487630,
  "lat": "31.2417561",
  "lon": "34.4072666",
  "class": "place",
  "type": "village",
  "place_rank": 19,
  "importance": 0.31901852752976795,
  "addresstype": "village",
  "name": "מבטחים",
  "display_name": "מבטחים, מועצה אזורית אשכול, נפת באר שבע, מחוז הדרום, ישראל",
  "boundingbox": [
    "31.2329914",
    "31.2464302",
    "34.4013983",
    "34.4148960"
  ],
  "geojson": {
    "type": "Polygon",
    "coordinates": [
      [
        [
          34.4013983,
          31.2403756
        ],
        [
          34.402238,
          31.2392319
        ],
        [
          34.4040372,
          31.240729
        ],
        [
          34.4043723,
          31.2404395
        ],
        [
          34.4040495,
          31.2400945
        ],
        [
          34.4049625,
          31.2393613
        ],
        [
          34.40585,
          31.2402197
        ],
        [
          34.40619,
          31.2399763
        ],
        [
          34.4063831,
          31.2401431
        ],
        [
          34.4065355,
          31.240032
        ],
        [
          34.4049772,
          31.2384928
        ],
        [
          34.405114,
          31.2382532
        ],
        [
          34.4065146,
          31.2395649
        ],
        [
          34.4067158,
          31.2394603
        ],
        [
          34.4052507,
          31.2380136
        ],
        [
          34.4053978,
          31.2377616
        ],
        [
          34.4071041,
          31.239381
        ],
        [
          34.4078429,
          31.2389024
        ],
        [
          34.4066609,
          31.2377673
        ],
        [
          34.4069111,
          31.2375547
        ],
        [
          34.4075182,
          31.2381503
        ],
        [
          34.4079661,
          31.2377942
        ],
        [
          34.4077313,
          31.2375489
        ],
        [
          34.4079829,
          31.2373818
        ],
        [
          34.4074302,
          31.2368304
        ],
        [
          34.4076441,
          31.2366582
        ],
        [
          34.4080317,
          31.2370233
        ],
        [
          34.4081276,
          31.2368236
        ],
        [
          34.4077464,
          31.23646
        ],
        [
          34.4085219,
          31.2357828
        ],
        [
          34.4090044,
          31.2362056
        ],
        [
          34.4090844,
          31.2360085
        ],
        [
          34.409458,
          31.2345524
        ],
        [
          34.4100321,
          31.2347513
        ],
        [
          34.410217,
          31.2347777
        ],
        [
          34.4104268,
          31.2346584
        ],
        [
          34.4101499,
          31.2343187
        ],
        [
          34.4100757,
          31.2342247
        ],
        [
          34.4100488,
          31.2340848
        ],
        [
          34.4100775,
          31.233821
        ],
        [
          34.4101808,
          31.2335622
        ],
        [
          34.4112933,
          31.2329914
        ],
        [
          34.411942,
          31.2337209
        ],
        [
          34.4095722,
          31.2354719
        ],
        [
          34.4100752,
          31.2359947
        ],
        [
          34.409682,
          31.2362875
        ],
        [
          34.4101017,
          31.236742
        ],
        [
          34.4104682,
          31.2364807
        ],
        [
          34.4107151,
          31.2367304
        ],
        [
          34.4095613,
          31.2375292
        ],
        [
          34.4094414,
          31.2380604
        ],
        [
          34.4097003,
          31.2381418
        ],
        [
          34.4098551,
          31.2383828
        ],
        [
          34.4092078,
          31.2388603
        ],
        [
          34.4093732,
          31.2390079
        ],
        [
          34.4096452,
          31.2388256
        ],
        [
          34.409964,
          31.2391241
        ],
        [
          34.409733,
          31.239291
        ],
        [
          34.409616,
          31.2391926
        ],
        [
          34.4089802,
          31.239601
        ],
        [
          34.408858,
          31.2399915
        ],
        [
          34.4087691,
          31.2401454
        ],
        [
          34.4082569,
          31.2404812
        ],
        [
          34.4085167,
          31.2405866
        ],
        [
          34.4089964,
          31.2402797
        ],
        [
          34.4093967,
          31.2406786
        ],
        [
          34.409591,
          31.24055
        ],
        [
          34.4097623,
          31.2407288
        ],
        [
          34.4105729,
          31.2401673
        ],
        [
          34.4107746,
          31.2403821
        ],
        [
          34.4106165,
          31.2404927
        ],
        [
          34.4108611,
          31.2407144
        ],
        [
          34.4104762,
          31.240985
        ],
        [
          34.410617,
          31.2411426
        ],
        [
          34.4101249,
          31.2414722
        ],
        [
          34.4103252,
          31.2416525
        ],
        [
          34.410527,
          31.2414909
        ],
        [
          34.4108552,
          31.24177
        ],
        [
          34.4104723,
          31.2420949
        ],
        [
          34.4114213,
          31.2420648
        ],
        [
          34.4113511,
          31.2416807
        ],
        [
          34.4111224,
          31.2414621
        ],
        [
          34.411635,
          31.2411265
        ],
        [
          34.4118561,
          31.2413375
        ],
        [
          34.4124293,
          31.2409786
        ],
        [
          34.4128242,
          31.2413677
        ],
        [
          34.4129148,
          31.2412993
        ],
        [
          34.4131549,
          31.2415262
        ],
        [
          34.4134482,
          31.2413439
        ],
        [
          34.4144967,
          31.2423695
        ],
        [
          34.4143945,
          31.2424367
        ],
        [
          34.4138975,
          31.2426574
        ],
        [
          34.4144847,
          31.2430536
        ],
        [
          34.4146209,
          31.2429886
        ],
        [
          34.414896,
          31.2432881
        ],
        [
          34.4145624,
          31.2435583
        ],
        [
          34.414385,
          31.2433993
        ],
        [
          34.414231,
          31.2435171
        ],
        [
          34.4136408,
          31.2430121
        ],
        [
          34.4132287,
          31.2433774
        ],
        [
          34.4122249,
          31.2426126
        ],
        [
          34.4118147,
          31.2429038
        ],
        [
          34.4115606,
          31.2426544
        ],
        [
          34.4113321,
          31.2428009
        ],
        [
          34.4115532,
          31.2430108
        ],
        [
          34.4112861,
          31.2432137
        ],
        [
          34.4109968,
          31.2429581
        ],
        [
          34.4107975,
          31.2431279
        ],
        [
          34.4104915,
          31.2428593
        ],
        [
          34.4102366,
          31.2430596
        ],
        [
          34.4105295,
          31.2433304
        ],
        [
          34.4103319,
          31.2434941
        ],
        [
          34.4101941,
          31.2433617
        ],
        [
          34.4099539,
          31.2435613
        ],
        [
          34.4106478,
          31.2442034
        ],
        [
          34.4101382,
          31.2445961
        ],
        [
          34.4095097,
          31.2440424
        ],
        [
          34.4093486,
          31.2441823
        ],
        [
          34.4086317,
          31.2435555
        ],
        [
          34.4083045,
          31.2437917
        ],
        [
          34.4083986,
          31.2438848
        ],
        [
          34.4081563,
          31.2441547
        ],
        [
          34.4079604,
          31.2440517
        ],
        [
          34.4077966,
          31.2443051
        ],
        [
          34.4082772,
          31.2446146
        ],
        [
          34.4084747,
          31.2452061
        ],
        [
          34.4080817,
          31.2453172
        ],
        [
          34.4080094,
          31.2451943
        ],
        [
          34.4076447,
          31.2454038
        ],
        [
          34.4078606,
          31.2458624
        ],
        [
          34.407852,
          31.2462844
        ],
        [
          34.4073516,
          31.2464302
        ],
        [
          34.4072084,
          31.2460559
        ],
        [
          34.4068811,
          31.2461457
        ],
        [
          34.4066326,
          31.2454801
        ],
        [
          34.4064533,
          31.2450799
        ],
        [
          34.406735,
          31.2449376
        ],
        [
          34.4062029,
          31.2436685
        ],
        [
          34.4060806,
          31.2434603
        ],
        [
          34.4059841,
          31.2434381
        ],
        [
          34.4059447,
          31.2433398
        ],
        [
          34.4053265,
          31.2437864
        ],
        [
          34.4045574,
          31.2428495
        ],
        [
          34.4043404,
          31.2429577
        ],
        [
          34.404191,
          31.2427791
        ],
        [
          34.4044259,
          31.2426103
        ],
        [
          34.404038,
          31.242122
        ],
        [
          34.4033667,
          31.2425731
        ],
        [
          34.4029398,
          31.2421434
        ],
        [
          34.4033871,
          31.2418152
        ],
        [
          34.4030381,
          31.2414268
        ],
        [
          34.403318,
          31.2412291
        ],
        [
          34.403119,
          31.2410504
        ],
        [
          34.4027394,
          31.2412977
        ],
        [
          34.4025437,
          31.2411139
        ],
        [
          34.4026814,
          31.2410363
        ],
        [
          34.4023755,
          31.2407808
        ],
        [
          34.4020635,
          31.2410322
        ],
        [
          34.4013983,
          31.2403756
        ]
      ]
    ]
  }
}