{
  "place_id": 186973658,
  "licence": "Data © OpenStreetMap contributors, ODbL 1.0. http://osm.org/copyright",
  "osm_type": "way",
  "osm_id": 682943899,
  "lat": "32.9290739",
  "lon": "35.2447876",
  "class": "place",
  "type": "village",
  "place_rank": 19,
  "importance": 0.3292608781983973,
  "addresstype": "village",
  "name": "תובל",
  "display_name": "תובל, מועצה אזורית משגב, נפת עכו, מחוז הצפון, ישראל",
  "boundingbox": [
    "32.9259905",
    "32.9320883",
    "35.2413485",
    "35.2516347"
  ],
  "geojson": {
    "type": "Polygon",
    "coordinates": [
      [
        [
          35.2413485,
          32.9282307
        ],
        [
          35.2424755,
          32.9279341
        ],
        [
          35.2423822,
          32.9276701
        ],
        [
          35.2425723,
          32.9274838
        ],
        [
          35.2417971,
          32.9269226
        ],
        [
          35.2421295,
          32.9265923
        ],
        [
          35.2424317,
          32.9263632
        ],
        [
          35.2427102,
          32.9262261
        ],
        [
          35.2430077,
          32.9260866
        ],
        [
          35.2434271,
          32.9260342
        ],
        [
          35.2441145,
          32.9259905
        ],
        [
          35.2441846,
          32.9260913
        ],
        [
          35.2442593,
          32.9263478
        ],
        [
          35.2443311,
          32.926383
        ],
        [
          35.2453181,
          32.9266131
        ],
        [
          35.2448718,
          32.9279099
        ],
        [
          35.2454297,
          32.9280256
        ],
        [
          35.2457124,
          32.928746
        ],
        [
          35.2465026,
          32.9284651
        ],
        [
          35.2467773,
          32.9291423
        ],
        [
          35.247369,
          32.9289905
        ],
        [
          35.2477471,
          32.9298267
        ],
        [
          35.2485196,
          32.9296389
        ],
        [
          35.2490598,
          32.9302229
        ],
        [
          35.2499272,
          32.9298911
        ],
        [
          35.2503473,
          32.9299419
        ],
        [
          35.250674,
          32.9299991
        ],
        [
          35.2508886,
          32.9301148
        ],
        [
          35.2510339,
          32.9303233
        ],
        [
          35.2516347,
          32.9313539
        ],
        [
          35.2514808,
          32.931462
        ],
        [
          35.2488452,
          32.9320523
        ],
        [
          35.2484161,
          32.9320883
        ],
        [
          35.2461936,
          32.9301869
        ],
        [
          35.2456266,
          32.9303021
        ],
        [
          35.2451488,
          32.9303208
        ],
        [
          35.2451423,
          32.9305817
        ],
        [
          35.2450699,
          32.9306486
        ],
        [
          35.2449267,
          32.9306799
        ],
        [
          35.2441805,
          32.9307139
        ],
        [
          35.2438794,
          32.9306719
        ],
        [
          35.2435891,
          32.9305761
        ],
        [
          35.2433692,
          32.9304548
        ],
        [
          35.2431579,
          32.9302861
        ],
        [
          35.2428784,
          32.9300188
        ],
        [
          35.2426533,
          32.9297957
        ],
        [
          35.2425136,
          32.9295726
        ],
        [
          35.2423554,
          32.9293184
        ],
        [
          35.2418549,
          32.9295115
        ],
        [
          35.2418,
          32.9295261
        ],
        [
          35.2415814,
          32.928766
        ],
        [
          35.2413485,
          32.9282307
        ]
      ]
    ]
  }
}