[
  {
    "place_id": 371344941,
    "licence": "Data © OpenStreetMap contributors, ODbL 1.0. http://osm.org/copyright",
    "osm_type": "relation",
    "osm_id": 1378949,
    "lat": "33.26921375",
    "lon": "35.572338398071736",
    "class": "boundary",
    "type": "administrative",
    "place_rank": 16,
    "importance": 0.4395929376271782,
    "addresstype": "town",
    "name": "מטולה",
    "display_name": "מטולה, נפת צפת, מחוז הצפון, 1029200, ישראל",
    "boundingbox": [
      "33.2479139",
      "33.2904182",
      "35.5566675",
      "35.5965683"
    ],
    "geojson": {
      "type": "Polygon",
      "coordinates": [
        [
          [
            35.5566675,
            33.2617295
          ],
          [
            35.5568355,
            33.2617312
          ],
          [
            35.556943,
            33.2617174
          ],
          [
            35.5569855,
            33.26148
          ],
          [
            35.5573461,
            33.2604633
          ],
          [
            35.5576525,
            33.2600378
          ],
          [
            35.5576266,
            33.2594144
          ],
          [
            35.5577484,
            33.2585272
          ],
          [
            35.5577772,
            33.2579136
          ],
          [
            35.5576684,
            33.2570488
          ],
          [
            35.557635,
            33.2565818
          ],
          [
            35.5576591,
            33.2563224
          ],
          [
            35.5576738,
            33.2561959
          ],
          [
            35.55783,
            33.2563231
          ],
          [
            35.5584659,
            33.2563272
          ],
          [
            35.5584954,
            33.2561792
          ],
          [
            35.5584672,
            33.2560505
          ],
          [
            35.5584749,
            33.2555284
          ],
          [
            35.558196,
            33.2552638
          ],
          [
            35.5582469,
            33.2538793
          ],
          [
            35.5582439,
            33.2527092
          ],
          [
            35.5581031,
            33.25223
          ],
          [
            35.5577121,
            33.2518626
          ],
          [
            35.5580466,
            33.251736
          ],
          [
            35.558141,
            33.2517469
          ],
          [
            35.5587422,
            33.2516943
          ],
          [
            35.5592502,
            33.2520801
          ],
          [
            35.5592955,
            33.2523248
          ],
          [
            35.559536,
            33.2526981
          ],
          [
            35.5596652,
            33.2529852
          ],
          [
            35.559666,
            33.2530834
          ],
          [
            35.559824,
            33.2533518
          ],
          [
            35.559931,
            33.2534433
          ],
          [
            35.560291,
            33.2535236
          ],
          [
            35.5606753,
            33.2537454
          ],
          [
            35.5607451,
            33.2537572
          ],
          [
            35.5626839,
            33.2538742
          ],
          [
            35.5634533,
            33.2542415
          ],
          [
            35.5638218,
            33.2545261
          ],
          [
            35.564844,
            33.2558361
          ],
          [
            35.5652197,
            33.2561431
          ],
          [
            35.5658759,
            33.2567565
          ],
          [
            35.5668579,
            33.2579009
          ],
          [
            35.5671294,
            33.258093
          ],
          [
            35.5672927,
            33.2581133
          ],
          [
            35.56744,
            33.2580684
          ],
          [
            35.5677905,
            33.2579
          ],
          [
            35.5684677,
            33.2579213
          ],
          [
            35.5685336,
            33.2579294
          ],
          [
            35.5687871,
            33.2580884
          ],
          [
            35.5689666,
            33.2581468
          ],
          [
            35.5694723,
            33.2581896
          ],
          [
            35.5695807,
            33.2580495
          ],
          [
            35.5698571,
            33.2579474
          ],
          [
            35.5701216,
            33.2579509
          ],
          [
            35.5705806,
            33.2578836
          ],
          [
            35.5707559,
            33.2578916
          ],
          [
            35.5709024,
            33.257843
          ],
          [
            35.5709453,
            33.2576464
          ],
          [
            35.5714052,
            33.256423
          ],
          [
            35.5716135,
            33.2557433
          ],
          [
            35.5717359,
            33.2554498
          ],
          [
            35.5720563,
            33.2549117
          ],
          [
            35.572086,
            33.2547859
          ],
          [
            35.5720656,
            33.2546546
          ],
          [
            35.5720032,
            33.2545479
          ],
          [
            35.5713917,
            33.2538102
          ],
          [
            35.5711975,
            33.2534711
          ],
          [
            35.5720386,
            33.253765
          ],
          [
            35.5728685,
            33.253196
          ],
          [
            35.5742393,
            33.2532344
          ],
          [
            35.5745434,
            33.2531033
          ],
          [
            35.57534,
            33.2529465
          ],
          [
            35.5752449,
            33.2528067
          ],
          [
            35.5752388,
            33.2524743
          ],
          [
            35.575498,
            33.2524256
          ],
          [
            35.5756048,
            33.2522534
          ],
          [
            35.575601,
            33.2521447
          ],
          [
            35.5754784,
            33.2517968
          ],
          [
            35.5751218,
            33.2513318
          ],
          [
            35.5753105,
            33.2511757
          ],
          [
            35.575398,
            33.2510549
          ],
          [
            35.5754081,
            33.2509461
          ],
          [
            35.5753512,
            33.2506803
          ],
          [
            35.5751049,
            33.2504122
          ],
          [
            35.5748989,
            33.2499992
          ],
          [
            35.5750846,
            33.2498268
          ],
          [
            35.575254,
            33.2497857
          ],
          [
            35.5753789,
            33.2497154
          ],
          [
            35.5754551,
            33.2496391
          ],
          [
            35.5756513,
            33.2495692
          ],
          [
            35.5761552,
            33.2492375
          ],
          [
            35.5762588,
            33.2492197
          ],
          [
            35.5764145,
            33.2492582
          ],
          [
            35.5766225,
            33.249426
          ],
          [
            35.5773465,
            33.2493946
          ],
          [
            35.5774281,
            33.2493763
          ],
          [
            35.5775087,
            33.2493231
          ],
          [
            35.5778145,
            33.2492562
          ],
          [
            35.5779509,
            33.2490617
          ],
          [
            35.5783181,
            33.248978
          ],
          [
            35.5784989,
            33.2490239
          ],
          [
            35.578579,
            33.2491673
          ],
          [
            35.5787956,
            33.2491713
          ],
          [
            35.5788986,
            33.2491226
          ],
          [
            35.5793984,
            33.2491401
          ],
          [
            35.5796814,
            33.2492326
          ],
          [
            35.5801522,
            33.2492925
          ],
          [
            35.5804263,
            33.2492495
          ],
          [
            35.5807134,
            33.2491257
          ],
          [
            35.5808436,
            33.2491023
          ],
          [
            35.5811157,
            33.2492337
          ],
          [
            35.5814605,
            33.2485774
          ],
          [
            35.5819052,
            33.2482969
          ],
          [
            35.5821314,
            33.2482306
          ],
          [
            35.5826807,
            33.2481567
          ],
          [
            35.582714,
            33.2482096
          ],
          [
            35.5826861,
            33.248394
          ],
          [
            35.5827041,
            33.2484407
          ],
          [
            35.582918,
            33.2486361
          ],
          [
            35.5831563,
            33.2487177
          ],
          [
            35.5834539,
            33.2484457
          ],
          [
            35.5840355,
            33.2480083
          ],
          [
            35.5841175,
            33.2480143
          ],
          [
            35.5849244,
            33.2484733
          ],
          [
            35.5852567,
            33.248345
          ],
          [
            35.5854166,
            33.2484437
          ],
          [
            35.585478,
            33.2485274
          ],
          [
            35.5855659,
            33.2485475
          ],
          [
            35.5859332,
            33.2484162
          ],
          [
            35.586064,
            33.2484124
          ],
          [
            35.5861865,
            33.2484813
          ],
          [
            35.5864734,
            33.2482984
          ],
          [
            35.5866526,
            33.2483182
          ],
          [
            35.5867598,
            33.2482992
          ],
          [
            35.5871005,
            33.2480638
          ],
          [
            35.5873328,
            33.2479379
          ],
          [
            35.5874385,
            33.2479139
          ],
          [
            35.587788,
            33.2479303
          ],
          [
            35.5880616,
            33.2481155
          ],
          [
            35.5882898,
            33.2482314
          ],
          [
            35.5884598,
            33.2482297
          ],
          [
            35.5886699,
            33.2481649
          ],
          [
            35.5886498,
            33.2482587
          ],
          [
            35.5885592,
            33.248704
          ],
          [
            35.5882225,
            33.249166
          ],
          [
            35.5876372,
            33.2503643
          ],
          [
            35.5874323,
            33.2510226
          ],
          [
            35.5873766,
            33.2513561
          ],
          [
            35.5869512,
            33.2521177
          ],
          [
            35.5861716,
            33.2529919
          ],
          [
            35.5872596,
            33.2531787
          ],
          [
            35.5882715,
            33.2531552
          ],
          [
            35.5887839,
            33.2531826
          ],
          [
            35.5893615,
            33.2533089
          ],
          [
            35.5902552,
            33.2535923
          ],
          [
            35.5906173,
            33.2538491
          ],
          [
            35.5908843,
            33.2542199
          ],
          [
            35.5911175,
            33.2547302
          ],
          [
            35.5912397,
            33.2551869
          ],
          [
            35.5914375,
            33.2561801
          ],
          [
            35.591498,
            33.2565791
          ],
          [
            35.5914957,
            33.2571086
          ],
          [
            35.5913507,
            33.258012
          ],
          [
            35.5914651,
            33.2592431
          ],
          [
            35.5920584,
            33.2592579
          ],
          [
            35.5925248,
            33.2591432
          ],
          [
            35.5938161,
            33.2581637
          ],
          [
            35.5954604,
            33.2576334
          ],
          [
            35.5965683,
            33.2572354
          ],
          [
            35.5954967,
            33.2590243
          ],
          [
            35.5944876,
            33.2604243
          ],
          [
            35.593799,
            33.2610909
          ],
          [
            35.5931904,
            33.2614829
          ],
          [
            35.5928642,
            33.2616245
          ],
          [
            35.5909007,
            33.2624769
          ],
          [
            35.5906947,
            33.2625627
          ],
          [
            35.590171,
            33.2628332
          ],
          [
            35.5897396,
            33.2632037
          ],
          [
            35.5889882,
            33.2637354
          ],
          [
            35.5874854,
            33.2646308
          ],
          [
            35.5854615,
            33.2657765
          ],
          [
            35.5848907,
            33.2659127
          ],
          [
            35.5842728,
            33.2659157
          ],
          [
            35.5838932,
            33.2659616
          ],
          [
            35.5837167,
            33.2660838
          ],
          [
            35.5835775,
            33.2663095
          ],
          [
            35.5834711,
            33.266653
          ],
          [
            35.5835692,
            33.2672168
          ],
          [
            35.5836999,
            33.2676116
          ],
          [
            35.5837757,
            33.2678129
          ],
          [
            35.5839531,
            33.2681028
          ],
          [
            35.584101,
            33.2683649
          ],
          [
            35.584101,
            33.2686907
          ],
          [
            35.5842703,
            33.2692765
          ],
          [
            35.5846845,
            33.2703968
          ],
          [
            35.5848463,
            33.2708911
          ],
          [
            35.5850276,
            33.271513
          ],
          [
            35.585406,
            33.2727598
          ],
          [
            35.5855527,
            33.2733758
          ],
          [
            35.5855543,
            33.2740493
          ],
          [
            35.5849053,
            33.2763328
          ],
          [
            35.5849041,
            33.2765357
          ],
          [
            35.5848949,
            33.2792752
          ],
          [
            35.5848125,
            33.2803182
          ],
          [
            35.5847701,
            33.2809259
          ],
          [
            35.5846725,
            33.2815363
          ],
          [
            35.5845866,
            33.2817016
          ],
          [
            35.5844655,
            33.2818618
          ],
          [
            35.5835393,
            33.2825515
          ],
          [
            35.5825459,
            33.2832082
          ],
          [
            35.5820688,
            33.2831797
          ],
          [
            35.5817946,
            33.2831118
          ],
          [
            35.5815667,
            33.2831653
          ],
          [
            35.5804152,
            33.2847653
          ],
          [
            35.5803377,
            33.284873
          ],
          [
            35.5792512,
            33.285446
          ],
          [
            35.5780983,
            33.286054
          ],
          [
            35.5768047,
            33.2867535
          ],
          [
            35.5762315,
            33.2869408
          ],
          [
            35.5756822,
            33.2870405
          ],
          [
            35.5751106,
            33.2872269
          ],
          [
            35.5740095,
            33.2873681
          ],
          [
            35.5730112,
            33.2874905
          ],
          [
            35.5720529,
            33.2876284
          ],
          [
            35.5714596,
            33.2879233
          ],
          [
            35.5708528,
            33.2883721
          ],
          [
            35.5705747,
            33.2886571
          ],
          [
            35.5703408,
            33.2889681
          ],
          [
            35.5700916,
            33.2893358
          ],
          [
            35.5700125,
            33.2894109
          ],
          [
            35.569843,
            33.2895721
          ],
          [
            35.5696662,
            33.2897401
          ],
          [
            35.5693406,
            33.2899712
          ],
          [
            35.5689035,
            33.2902645
          ],
          [
            35.56856,
            33.2903792
          ],
          [
            35.5683207,
            33.2904157
          ],
          [
            35.5680776,
            33.2904182
          ],
          [
            35.5679557,
            33.2903822
          ],
          [
            35.567828,
            33.2903412
          ],
          [
            35.5674122,
            33.2900493
          ],
          [
            35.5671875,
            33.2898605
          ],
          [
            35.5668474,
            33.2895747
          ],
          [
            35.5666585,
            33.289416
          ],
          [
            35.5662176,
            33.2890434
          ],
          [
            35.5657836,
            33.2886767
          ],
          [
            35.5654857,
            33.288351
          ],
          [
            35.5653318,
            33.2881829
          ],
          [
            35.5649073,
            33.2877202
          ],
          [
            35.5646982,
            33.2873139
          ],
          [
            35.5646135,
            33.2871501
          ],
          [
            35.5644884,
            33.2867982
          ],
          [
            35.5644255,
            33.2866213
          ],
          [
            35.5643831,
            33.2865018
          ],
          [
            35.5643507,
            33.2864114
          ],
          [
            35.5642742,
            33.2861982
          ],
          [
            35.5642028,
            33.2859993
          ],
          [
            35.5641634,
            33.2858894
          ],
          [
            35.5641218,
            33.2857915
          ],
          [
            35.5640398,
            33.2855987
          ],
          [
            35.5639621,
            33.2854162
          ],
          [
            35.5639115,
            33.2852972
          ],
          [
            35.5638801,
            33.285223
          ],
          [
            35.5638176,
            33.2850514
          ],
          [
            35.5637953,
            33.2849902
          ],
          [
            35.5637445,
            33.2848504
          ],
          [
            35.5636797,
            33.2846724
          ],
          [
            35.5636714,
            33.2846496
          ],
          [
            35.5635933,
            33.2844771
          ],
          [
            35.5634995,
            33.2842698
          ],
          [
            35.5634562,
            33.2841741
          ],
          [
            35.5634106,
            33.2840733
          ],
          [
            35.5633826,
            33.2840115
          ],
          [
            35.5633723,
            33.2839886
          ],
          [
            35.5633575,
            33.2839254
          ],
          [
            35.5633462,
            33.2838771
          ],
          [
            35.5633378,
            33.2838414
          ],
          [
            35.563312,
            33.2837314
          ],
          [
            35.5633037,
            33.2836959
          ],
          [
            35.5632955,
            33.2836604
          ],
          [
            35.5632769,
            33.2835802
          ],
          [
            35.5632757,
            33.2835741
          ],
          [
            35.5632654,
            33.283522
          ],
          [
            35.5632583,
            33.2834865
          ],
          [
            35.563227,
            33.2833289
          ],
          [
            35.5632111,
            33.2832489
          ],
          [
            35.5632166,
            33.2831652
          ],
          [
            35.5632006,
            33.2830015
          ],
          [
            35.5632179,
            33.2828137
          ],
          [
            35.5632357,
            33.2826422
          ],
          [
            35.5632969,
            33.2824959
          ],
          [
            35.5633096,
            33.2823986
          ],
          [
            35.5633227,
            33.2823022
          ],
          [
            35.5633444,
            33.2821415
          ],
          [
            35.563368,
            33.2819674
          ],
          [
            35.5633772,
            33.2818997
          ],
          [
            35.5634013,
            33.2817837
          ],
          [
            35.5634388,
            33.2816235
          ],
          [
            35.5634656,
            33.281521
          ],
          [
            35.5634909,
            33.2814246
          ],
          [
            35.5635161,
            33.2813116
          ],
          [
            35.5635566,
            33.2811305
          ],
          [
            35.5635998,
            33.2809368
          ],
          [
            35.5636499,
            33.2807125
          ],
          [
            35.5636956,
            33.280508
          ],
          [
            35.563738,
            33.2803182
          ],
          [
            35.5637821,
            33.2801524
          ],
          [
            35.5637871,
            33.2800984
          ],
          [
            35.5638179,
            33.2799607
          ],
          [
            35.5638628,
            33.2797596
          ],
          [
            35.5639073,
            33.2795603
          ],
          [
            35.5639437,
            33.2793973
          ],
          [
            35.5639851,
            33.2792119
          ],
          [
            35.5640241,
            33.2790371
          ],
          [
            35.5640603,
            33.278875
          ],
          [
            35.5640989,
            33.2787025
          ],
          [
            35.5641378,
            33.2785284
          ],
          [
            35.5641783,
            33.2783467
          ],
          [
            35.56422,
            33.2781599
          ],
          [
            35.5642589,
            33.2779861
          ],
          [
            35.5642961,
            33.2778194
          ],
          [
            35.5643362,
            33.2776398
          ],
          [
            35.5643798,
            33.2774444
          ],
          [
            35.5644235,
            33.2772492
          ],
          [
            35.5644668,
            33.277055
          ],
          [
            35.5645091,
            33.2768657
          ],
          [
            35.5645525,
            33.2766714
          ],
          [
            35.564596,
            33.2764764
          ],
          [
            35.564618,
            33.2762819
          ],
          [
            35.5646697,
            33.2760766
          ],
          [
            35.5647177,
            33.2758825
          ],
          [
            35.5647453,
            33.2757895
          ],
          [
            35.5647713,
            33.2756917
          ],
          [
            35.5648124,
            33.2755077
          ],
          [
            35.5648451,
            33.2752785
          ],
          [
            35.5648744,
            33.2750982
          ],
          [
            35.5648515,
            33.2749508
          ],
          [
            35.5648161,
            33.274776
          ],
          [
            35.5647959,
            33.2746766
          ],
          [
            35.5647885,
            33.2746577
          ],
          [
            35.5647651,
            33.2745976
          ],
          [
            35.5646903,
            33.2744054
          ],
          [
            35.5646129,
            33.2742065
          ],
          [
            35.5645354,
            33.2740075
          ],
          [
            35.5644897,
            33.2738902
          ],
          [
            35.5644451,
            33.2737755
          ],
          [
            35.5644024,
            33.2736658
          ],
          [
            35.5643845,
            33.2736245
          ],
          [
            35.5643221,
            33.2734806
          ],
          [
            35.564255,
            33.273326
          ],
          [
            35.5642007,
            33.2732007
          ],
          [
            35.564119,
            33.2730788
          ],
          [
            35.5640325,
            33.2729498
          ],
          [
            35.5639328,
            33.2728011
          ],
          [
            35.5638437,
            33.2726681
          ],
          [
            35.563747,
            33.2725239
          ],
          [
            35.5636604,
            33.2723948
          ],
          [
            35.5635678,
            33.2722641
          ],
          [
            35.5634715,
            33.2721282
          ],
          [
            35.5633675,
            33.2719815
          ],
          [
            35.5632569,
            33.2718252
          ],
          [
            35.5631661,
            33.2716971
          ],
          [
            35.563072,
            33.2715643
          ],
          [
            35.562963,
            33.2714206
          ],
          [
            35.5628461,
            33.2712746
          ],
          [
            35.5627101,
            33.271122
          ],
          [
            35.5625843,
            33.2709892
          ],
          [
            35.5624485,
            33.2708627
          ],
          [
            35.562316,
            33.2707601
          ],
          [
            35.5621866,
            33.270655
          ],
          [
            35.5620421,
            33.2705414
          ],
          [
            35.5619092,
            33.2704384
          ],
          [
            35.5617633,
            33.27032
          ],
          [
            35.5616204,
            33.2702084
          ],
          [
            35.5615024,
            33.2701129
          ],
          [
            35.5613226,
            33.2699687
          ],
          [
            35.5611802,
            33.2698438
          ],
          [
            35.5608737,
            33.2696113
          ],
          [
            35.5607652,
            33.2695391
          ],
          [
            35.5606271,
            33.2694155
          ],
          [
            35.5605017,
            33.2692871
          ],
          [
            35.5603587,
            33.269151
          ],
          [
            35.5603097,
            33.2690864
          ],
          [
            35.560231,
            33.268973
          ],
          [
            35.5601385,
            33.2688421
          ],
          [
            35.5600499,
            33.2687187
          ],
          [
            35.5599896,
            33.2686299
          ],
          [
            35.5599424,
            33.2685506
          ],
          [
            35.5598512,
            33.2684187
          ],
          [
            35.5597475,
            33.2682497
          ],
          [
            35.5596708,
            33.2680955
          ],
          [
            35.5596128,
            33.2679789
          ],
          [
            35.5595995,
            33.267923
          ],
          [
            35.5595612,
            33.2677626
          ],
          [
            35.5595417,
            33.2676809
          ],
          [
            35.5595441,
            33.2675705
          ],
          [
            35.5595478,
            33.2673953
          ],
          [
            35.5595517,
            33.2672137
          ],
          [
            35.5595543,
            33.2670944
          ],
          [
            35.5595565,
            33.2670322
          ],
          [
            35.5595616,
            33.2668886
          ],
          [
            35.5595677,
            33.2667183
          ],
          [
            35.5595728,
            33.2665727
          ],
          [
            35.559577,
            33.2665138
          ],
          [
            35.5595524,
            33.2664333
          ],
          [
            35.559531,
            33.2662794
          ],
          [
            35.5595491,
            33.2661672
          ],
          [
            35.5594458,
            33.2660569
          ],
          [
            35.5593449,
            33.2659766
          ],
          [
            35.5592187,
            33.265887
          ],
          [
            35.5590839,
            33.2657793
          ],
          [
            35.5589498,
            33.2657015
          ],
          [
            35.558833,
            33.2656284
          ],
          [
            35.5587228,
            33.2655449
          ],
          [
            35.5585979,
            33.2654823
          ],
          [
            35.5584674,
            33.2653998
          ],
          [
            35.5583307,
            33.2653159
          ],
          [
            35.5581764,
            33.2652097
          ],
          [
            35.5580928,
            33.2651521
          ],
          [
            35.5579953,
            33.2650904
          ],
          [
            35.557888,
            33.2650209
          ],
          [
            35.5577324,
            33.2649211
          ],
          [
            35.5573358,
            33.2646361
          ],
          [
            35.5571481,
            33.2644745
          ],
          [
            35.5570238,
            33.2642474
          ],
          [
            35.5569548,
            33.264019
          ],
          [
            35.5569091,
            33.263718
          ],
          [
            35.5568866,
            33.2636014
          ],
          [
            35.5568852,
            33.2634462
          ],
          [
            35.5568846,
            33.2633122
          ],
          [
            35.5568694,
            33.2631458
          ],
          [
            35.5568545,
            33.2630088
          ],
          [
            35.5568422,
            33.2628567
          ],
          [
            35.5568189,
            33.2627248
          ],
          [
            35.5567887,
            33.2625322
          ],
          [
            35.5567438,
            33.2621733
          ],
          [
            35.5567205,
            33.2620569
          ],
          [
            35.5567042,
            33.2619554
          ],
          [
            35.5566843,
            33.2618587
          ],
          [
            35.5566675,
            33.2617295
          ]
        ]
      ]
    }
  },
  {
    "place_id": 186202250,
    "licence": "Data © OpenStreetMap contributors, ODbL 1.0. http://osm.org/copyright",
    "osm_type": "way",
    "osm_id": 717602462,
    "lat": "33.2799815",
    "lon": "35.5779451",
    "class": "place",
    "type": "village",
    "place_rank": 19,
    "importance": 0.4395929376271782,
    "addresstype": "village",
    "name": "מטולה",
    "display_name": "מטולה, נפת צפת, מחוז הצפון, 1029200, ישראל",
    "boundingbox": [
      "33.2717301",
      "33.2862388",
      "35.5685876",
      "35.5839556"
    ],
    "geojson": {
      "type": "Polygon",
      "coordinates": [
        [
          [
            35.5685876,
            33.2765452
          ],
          [
            35.5686007,
            33.2763658
          ],
          [
            35.5688065,
            33.2751134
          ],
          [
            35.5688497,
            33.2749914
          ],
          [
            35.5689223,
            33.2749089
          ],
          [
            35.5689738,
            33.2748658
          ],
          [
            35.5690642,
            33.2748551
          ],
          [
            35.5691286,
            33.2748551
          ],
          [
            35.5692144,
            33.2748909
          ],
          [
            35.5701454,
            33.2760678
          ],
          [
            35.5704161,
            33.2763369
          ],
          [
            35.5706564,
            33.2764914
          ],
          [
            35.5707935,
            33.2765559
          ],
          [
            35.5711582,
            33.2766777
          ],
          [
            35.5713988,
            33.2767136
          ],
          [
            35.5716732,
            33.2767246
          ],
          [
            35.5719951,
            33.2767028
          ],
          [
            35.5724503,
            33.2765844
          ],
          [
            35.5726388,
            33.2771692
          ],
          [
            35.5729867,
            33.2776144
          ],
          [
            35.5727764,
            33.2777327
          ],
          [
            35.5725101,
            33.2778689
          ],
          [
            35.572712,
            33.2781918
          ],
          [
            35.5725618,
            33.2784537
          ],
          [
            35.5723687,
            33.2786546
          ],
          [
            35.5720683,
            33.2787553
          ],
          [
            35.5715445,
            33.2787732
          ],
          [
            35.571802,
            33.278834
          ],
          [
            35.5718966,
            33.2789093
          ],
          [
            35.5719264,
            33.2790134
          ],
          [
            35.572141,
            33.278956
          ],
          [
            35.5724629,
            33.2793865
          ],
          [
            35.5726305,
            33.2793437
          ],
          [
            35.5727592,
            33.2793363
          ],
          [
            35.5729693,
            33.2793721
          ],
          [
            35.5731624,
            33.2793616
          ],
          [
            35.5734327,
            33.2793004
          ],
          [
            35.5736473,
            33.2792217
          ],
          [
            35.5741408,
            33.2789526
          ],
          [
            35.5746,
            33.2793472
          ],
          [
            35.5750936,
            33.2796089
          ],
          [
            35.5753685,
            33.2797883
          ],
          [
            35.5755871,
            33.2800359
          ],
          [
            35.5758231,
            33.2803985
          ],
          [
            35.5764583,
            33.2802083
          ],
          [
            35.5763596,
            33.279878
          ],
          [
            35.576381,
            33.2797704
          ],
          [
            35.5767458,
            33.2797345
          ],
          [
            35.5767029,
            33.2792789
          ],
          [
            35.5766688,
            33.2788376
          ],
          [
            35.5764113,
            33.2788304
          ],
          [
            35.5764797,
            33.2784429
          ],
          [
            35.5765741,
            33.2781274
          ],
          [
            35.5764628,
            33.2780805
          ],
          [
            35.5766645,
            33.2775711
          ],
          [
            35.5765098,
            33.2774563
          ],
          [
            35.5767075,
            33.2770867
          ],
          [
            35.5768531,
            33.2767674
          ],
          [
            35.5770891,
            33.2764696
          ],
          [
            35.577338,
            33.2762005
          ],
          [
            35.577381,
            33.2761288
          ],
          [
            35.577381,
            33.2760678
          ],
          [
            35.5773726,
            33.2758597
          ],
          [
            35.5774239,
            33.2757771
          ],
          [
            35.5783551,
            33.2753681
          ],
          [
            35.5786,
            33.2753215
          ],
          [
            35.5787502,
            33.2753394
          ],
          [
            35.579016,
            33.2754616
          ],
          [
            35.5788833,
            33.275117
          ],
          [
            35.5787156,
            33.275049
          ],
          [
            35.578497,
            33.275067
          ],
          [
            35.5778402,
            33.2752964
          ],
          [
            35.5778919,
            33.275178
          ],
          [
            35.5780636,
            33.2750273
          ],
          [
            35.5782224,
            33.2749017
          ],
          [
            35.5783854,
            33.2746398
          ],
          [
            35.5784713,
            33.2743924
          ],
          [
            35.5784756,
            33.2741913
          ],
          [
            35.5784624,
            33.2736031
          ],
          [
            35.5786555,
            33.273384
          ],
          [
            35.5787888,
            33.2732656
          ],
          [
            35.5786816,
            33.2731546
          ],
          [
            35.5791877,
            33.2727922
          ],
          [
            35.5794023,
            33.2730649
          ],
          [
            35.579531,
            33.2730898
          ],
          [
            35.5795828,
            33.2731187
          ],
          [
            35.5798143,
            33.2737248
          ],
          [
            35.5801021,
            33.2736569
          ],
          [
            35.580145,
            33.2738684
          ],
          [
            35.579866,
            33.2739294
          ],
          [
            35.5800806,
            33.2745539
          ],
          [
            35.5801064,
            33.2746974
          ],
          [
            35.5804322,
            33.2750524
          ],
          [
            35.5805098,
            33.275067
          ],
          [
            35.5805784,
            33.2750344
          ],
          [
            35.5807155,
            33.2748802
          ],
          [
            35.5809604,
            33.2746544
          ],
          [
            35.5812651,
            33.2744391
          ],
          [
            35.581548,
            33.2742956
          ],
          [
            35.5817328,
            33.274152
          ],
          [
            35.5818616,
            33.2739978
          ],
          [
            35.5818914,
            33.2739222
          ],
          [
            35.581647,
            33.2738791
          ],
          [
            35.5812691,
            33.2737107
          ],
          [
            35.5816685,
            33.2729211
          ],
          [
            35.5817715,
            33.2728281
          ],
          [
            35.5819171,
            33.2727669
          ],
          [
            35.5821317,
            33.272731
          ],
          [
            35.5821274,
            33.2726233
          ],
          [
            35.5821577,
            33.2724155
          ],
          [
            35.5822175,
            33.2722002
          ],
          [
            35.5822478,
            33.2721284
          ],
          [
            35.5818957,
            33.2721284
          ],
          [
            35.5818957,
            33.2719165
          ],
          [
            35.5820075,
            33.2717301
          ],
          [
            35.5823337,
            33.2717371
          ],
          [
            35.5823677,
            33.2719131
          ],
          [
            35.5824965,
            33.2719849
          ],
          [
            35.5826984,
            33.2724513
          ],
          [
            35.5827843,
            33.2728065
          ],
          [
            35.5828398,
            33.2731905
          ],
          [
            35.5830329,
            33.2732763
          ],
          [
            35.5831574,
            33.2733732
          ],
          [
            35.5833076,
            33.2735851
          ],
          [
            35.583741,
            33.2743599
          ],
          [
            35.5839172,
            33.2748947
          ],
          [
            35.5839556,
            33.2751708
          ],
          [
            35.5831963,
            33.275404
          ],
          [
            35.5831018,
            33.2755296
          ],
          [
            35.5829731,
            33.2756482
          ],
          [
            35.5825995,
            33.2758417
          ],
          [
            35.582475,
            33.2756123
          ],
          [
            35.5819128,
            33.2758455
          ],
          [
            35.5819431,
            33.2759101
          ],
          [
            35.5817371,
            33.2759891
          ],
          [
            35.5819088,
            33.2763586
          ],
          [
            35.582239,
            33.2762292
          ],
          [
            35.5823205,
            33.2763765
          ],
          [
            35.5825439,
            33.2762761
          ],
          [
            35.5830461,
            33.2761108
          ],
          [
            35.5834237,
            33.2768535
          ],
          [
            35.5835908,
            33.2770834
          ],
          [
            35.5837625,
            33.2772807
          ],
          [
            35.5838912,
            33.2774888
          ],
          [
            35.5839127,
            33.277661
          ],
          [
            35.5838483,
            33.2778653
          ],
          [
            35.5835396,
            33.278253
          ],
          [
            35.583505,
            33.2783676
          ],
          [
            35.5835221,
            33.2785221
          ],
          [
            35.5836509,
            33.2788629
          ],
          [
            35.583741,
            33.2791066
          ],
          [
            35.5836981,
            33.2793398
          ],
          [
            35.5836337,
            33.2796627
          ],
          [
            35.5835181,
            33.2798675
          ],
          [
            35.5834495,
            33.2800072
          ],
          [
            35.5834108,
            33.2801794
          ],
          [
            35.5833934,
            33.2803229
          ],
          [
            35.5833679,
            33.2804343
          ],
          [
            35.5832606,
            33.2806709
          ],
          [
            35.5831831,
            33.2808649
          ],
          [
            35.5830179,
            33.281386
          ],
          [
            35.5811578,
            33.2816685
          ],
          [
            35.581132,
            33.2817795
          ],
          [
            35.5814236,
            33.2823138
          ],
          [
            35.5813209,
            33.2823643
          ],
          [
            35.5812519,
            33.282436
          ],
          [
            35.581235,
            33.2825042
          ],
          [
            35.5812734,
            33.2825975
          ],
          [
            35.5813807,
            33.2828017
          ],
          [
            35.5813807,
            33.2828916
          ],
          [
            35.5813423,
            33.2829598
          ],
          [
            35.5806511,
            33.283078
          ],
          [
            35.5802649,
            33.283078
          ],
          [
            35.5800334,
            33.2830062
          ],
          [
            35.579805,
            33.2829445
          ],
          [
            35.5802952,
            33.2844522
          ],
          [
            35.5801576,
            33.2846747
          ],
          [
            35.5798653,
            33.2848748
          ],
          [
            35.5791248,
            33.285229
          ],
          [
            35.57878,
            33.2846531
          ],
          [
            35.5775312,
            33.2851157
          ],
          [
            35.5773083,
            33.285148
          ],
          [
            35.5772393,
            33.2849363
          ],
          [
            35.5787773,
            33.2843258
          ],
          [
            35.5785614,
            33.2840038
          ],
          [
            35.5783466,
            33.2838244
          ],
          [
            35.578132,
            33.2836305
          ],
          [
            35.5780118,
            33.2834511
          ],
          [
            35.5777074,
            33.2828378
          ],
          [
            35.5762397,
            33.2830136
          ],
          [
            35.5760163,
            33.2831392
          ],
          [
            35.5760337,
            33.283419
          ],
          [
            35.5761364,
            33.2835515
          ],
          [
            35.5761364,
            33.2837168
          ],
          [
            35.5761281,
            33.2839572
          ],
          [
            35.5761579,
            33.2841724
          ],
          [
            35.5762268,
            33.2843733
          ],
          [
            35.5763126,
            33.2844809
          ],
          [
            35.5764454,
            33.284524
          ],
          [
            35.5766085,
            33.2847679
          ],
          [
            35.5764714,
            33.2848397
          ],
          [
            35.5768231,
            33.2855067
          ],
          [
            35.5767801,
            33.2856828
          ],
          [
            35.5766385,
            33.2858263
          ],
          [
            35.5764543,
            33.2858801
          ],
          [
            35.5762652,
            33.2859014
          ],
          [
            35.5761066,
            33.2859014
          ],
          [
            35.5760163,
            33.2859662
          ],
          [
            35.5759733,
            33.2860415
          ],
          [
            35.5754712,
            33.286192
          ],
          [
            35.5753385,
            33.2862388
          ],
          [
            35.5752488,
            33.2861167
          ],
          [
            35.5748151,
            33.2853992
          ],
          [
            35.5752142,
            33.2851945
          ],
          [
            35.574519,
            33.2841795
          ],
          [
            35.5739828,
            33.2844127
          ],
          [
            35.5736612,
            33.284036
          ],
          [
            35.5735236,
            33.283749
          ],
          [
            35.5734466,
            33.2835196
          ],
          [
            35.5734252,
            33.2833077
          ],
          [
            35.5738626,
            33.2831857
          ],
          [
            35.5737553,
            33.2828559
          ],
          [
            35.5737213,
            33.2826225
          ],
          [
            35.5733477,
            33.2826621
          ],
          [
            35.5733004,
            33.2824251
          ],
          [
            35.5732447,
            33.2821312
          ],
          [
            35.5731932,
            33.2818262
          ],
          [
            35.5736867,
            33.2819049
          ],
          [
            35.5738412,
            33.2811984
          ],
          [
            35.5739444,
            33.2810369
          ],
          [
            35.5730301,
            33.2805273
          ],
          [
            35.5727769,
            33.2803981
          ],
          [
            35.5726613,
            33.2802979
          ],
          [
            35.5725969,
            33.2801828
          ],
          [
            35.5726009,
            33.2800788
          ],
          [
            35.5726827,
            33.279842
          ],
          [
            35.572691,
            33.2797344
          ],
          [
            35.5726481,
            33.2795983
          ],
          [
            35.5724467,
            33.2795514
          ],
          [
            35.571675,
            33.2795579
          ],
          [
            35.5711987,
            33.2794897
          ],
          [
            35.5709498,
            33.2794254
          ],
          [
            35.5708975,
            33.2792823
          ],
          [
            35.5709876,
            33.2791209
          ],
          [
            35.5709916,
            33.2790242
          ],
          [
            35.5709661,
            33.2789594
          ],
          [
            35.5708374,
            33.2788735
          ],
          [
            35.5706228,
            33.2787693
          ],
          [
            35.5704165,
            33.2786258
          ],
          [
            35.5702449,
            33.2784715
          ],
          [
            35.5700864,
            33.2782957
          ],
          [
            35.5698415,
            33.2780555
          ],
          [
            35.5687378,
            33.2770295
          ],
          [
            35.5686305,
            33.2768822
          ],
          [
            35.5686007,
            33.2767566
          ],
          [
            35.5685876,
            33.2765452
          ]
        ]
      ]
    }
  }
]